Metadata-Version: 1.1
Name: hierarchy
Version: 0.1.2
Summary: Clone and Maintain an entire hierarchy of Git repositories in one command
Home-page: https://github.com/FlorianKempenich/Hierarchy
Author: Florian Kempenich
Author-email: Flori@nKempenich.com
License: MIT
Keywords: git batch
Platform: UNKNOWN
Classifier: Environment :: Console
Classifier: Intended Audience :: Developers
Classifier: License :: OSI Approved :: MIT License
Classifier: Topic :: Utilities
